{"ti.ui.defaultunit":"dp","run-on-main-thread":true,"appc-app-id":"58acf2b8833cb52120a3b20b","acs-authbase-url-development":"https://secure-identity.cloud.appcelerator.com","acs-base-url-development":"https://api.cloud.appcelerator.com","acs-oauth-secret-development":"H8kZoFgr5Q4vAOSKkmdP1EckzGlfRzQJ","acs-oauth-key-development":"jMbjgZyJnYVsuAeOpz0Htlft923f5r1M","acs-api-key-development":"ajpKmaPTZl9kc4PXvaAH6kZO0MxPaMsJ","acs-username-development":"appc_app_user_dev","acs-password-development":"qA4RHJvfOmCc5xavNL","acs-authbase-url-production":"https://secure-identity.cloud.appcelerator.com","acs-base-url-production":"https://api.cloud.appcelerator.com","acs-oauth-secret-production":"V2fKQTAkbaSsircQVeLq1VsXz9uYgZSA","acs-oauth-key-production":"pafvjzWvxVZEIJbHjyyC3zyBcNv2DkkD","acs-api-key-production":"GboF6TWLNF3y0JlLmuZSzgR3hfnAiZlp","acs-username-production":"appc_app_user","acs-password-production":"sPfpxjPNkRRwABo4hO","appc-org-id":"1293752342462","appc-creator-user-id":"0ab35d89-3de1-4c51-8744-4889e3392c32"}